{
	"arrayOfProducts": [
		{
			"imgUrl": "https://guesseu.scene7.com/is/image/GuessEU/M63H24W7JF0-L302-ALTGHOST?wid=1500&fmt=jpeg&qlt=80&op_sharpen=0&op_usm=1.0,1.0,5,0&iccEmbed=0",
			"name": "CHECK PRINT SHIRT",
			"price": 100,
			"discountedPrice": 2000,
			"type": "shirts",
			"description": "100% cotton double printed dress."
		},
		{
			"imgUrl": "https://guesseu.scene7.com/is/image/GuessEU/FLGLO4FAL12-BEIBR?wid=700&amp;fmt=jpeg&amp;qlt=80&amp;op_sharpen=0&amp;op_usm=1.0,1.0,5,0&amp;iccEmbed=0",
			"name": "GLORIA Shoes",
			"price": 100,
			"discountedPrice": 2000,
			"type": "shoes",
			"description": "100% cotton double printed dress."
		},
		{
			"imgUrl": "https://i.ibb.co/D957b79/b1.png",
			"name": "CATE RIGID BAG",
			"price": 100,
			"discountedPrice": 2000,
			"type": "bags",
			"description": "100% cotton double printed dress."
		},
		{
			"imgUrl": "http://guesseu.scene7.com/is/image/GuessEU/WC0001FMSWC-G5?wid=520&fmt=jpeg&qlt=80&op_sharpen=0&op_usm=1.0,1.0,5,0&iccEmbed=0",
			"name": "GUESS CONNECT WATCH",
			"price": 100,
			"discountedPrice": 2000,
			"type": "watches",
			"description": "100% cotton double printed dress."
		},
		{
			"imgUrl": "https://guesseu.scene7.com/is/image/GuessEU/AW6308VIS03-SAP?wid=700&amp;fmt=jpeg&amp;qlt=80&amp;op_sharpen=0&amp;op_usm=1.0,1.0,5,0&amp;iccEmbed=0",
			"name": "'70s RETRO GLAM SCARF",
			"price": 100,
			"discountedPrice": 2000,
			"type": "scarfs",
			"description": "100% cotton double printed dress."
		},
		{
			"imgUrl": "https://i.ibb.co/SNVyv7N/shirt1.jpg",
			"name": "CHECK PRINT SHIRT",
			"price": 200,
			"discountedPrice": 2000,
			"type": "shirts",
			"description": "100% cotton double printed dress."
		},
		{
			"imgUrl": "https://i.ibb.co/WPpJmz0/ss1.webp",
			"name": "GLORIA Shoes",
			"price": 200,
			"discountedPrice": 2000,
			"type": "shoes",
			"description": "100% cotton double printed dress."
		},
		{
			"imgUrl": "https://i.ibb.co/wcVj87s/s2.png",
			"name": "CATE RIGID BAG",
			"price": 200,
			"discountedPrice": 2000,
			"type": "bags",
			"description": "100% cotton double printed dress."
		},
		{
			"imgUrl": "https://i.ibb.co/Zg3Bkhh/w1.jpg",
			"name": "GUESS CONNECT WATCH",
			"price": 200,
			"discountedPrice": 2000,
			"type": "watches",
			"description": "100% cotton double printed dress."
		},
		{
			"imgUrl": "https://i.ibb.co/CWNrHCb/sc1.jpg",
			"name": "'70s RETRO GLAM SCARF",
			"price": 200,
			"discountedPrice": 2000,
			"type": "scarfs",
			"description": "100% cotton double printed dress."
		},
		{
			"imgUrl": "https://i.ibb.co/JC61ngd/shirt.jpg",
			"name": "CHECK PRINT SHIRT",
			"price": 300,
			"discountedPrice": 2000,
			"type": "shirts",
			"description": "100% cotton double printed dress."
		},
		{
			"imgUrl": "https://i.ibb.co/zr0Yqch/ss2.png",
			"name": "GLORIA Shoes",
			"price": 300,
			"discountedPrice": 2000,
			"type": "shoes",
			"description": "100% cotton double printed dress."
		},
		{
			"imgUrl": "https://i.ibb.co/mBk0Pqh/s3.jpg",
			"name": "CATE RIGID BAG",
			"price": 300,
			"discountedPrice": 2000,
			"type": "bags",
			"description": "100% cotton double printed dress."
		},
		{
			"imgUrl": "https://i.ibb.co/BVSLV2h/w2.jpg",
			"name": "GUESS CONNECT WATCH",
			"price": 300,
			"discountedPrice": 2000,
			"type": "watches",
			"description": "100% cotton double printed dress."
		},
		{
			"imgUrl": "https://i.ibb.co/MD3Z1tQ/sc2.webp",
			"name": "'70s RETRO GLAM SCARF",
			"price": 300,
			"discountedPrice": 2000,
			"type": "scarfs",
			"description": "100% cotton double printed dress."
		},
		{
			"imgUrl": "https://i.ibb.co/tbgvdxb/Shirt-PNG-Download-Image.png",
			"name": "CHECK PRINT SHIRT",
			"price": 400,
			"discountedPrice": 2000,
			"type": "shirts",
			"description": "100% cotton double printed dress."
		},
		{
			"imgUrl": "https://i.ibb.co/85jkr3h/ss3.jpg",
			"name": "GLORIA Shoes",
			"price": 400,
			"discountedPrice": 2000,
			"type": "shoes",
			"description": "100% cotton double printed dress."
		},
		{
			"imgUrl": "https://guesseu.scene7.com/is/image/GuessEU/HWVG6216060-TAN?wid=700&amp;fmt=jpeg&amp;qlt=80&amp;op_sharpen=0&amp;op_usm=1.0,1.0,5,0&amp;iccEmbed=0",
			"name": "CATE RIGID BAG",
			"price": 400,
			"discountedPrice": 2000,
			"type": "bags",
			"description": "100% cotton double printed dress."
		},
		{
			"imgUrl": "https://i.ibb.co/xGJYgj3/w3.jpg",
			"name": "GUESS CONNECT WATCH",
			"price": 400,
			"discountedPrice": 2000,
			"type": "watches",
			"description": "100% cotton double printed dress."
		},
		{
			"imgUrl": "https://i.ibb.co/8jqMg8y/sc3.jpg",
			"name": "'70s RETRO GLAM SCARF",
			"price": 400,
			"discountedPrice": 2000,
			"type": "scarfs",
			"description": "100% cotton double printed dress."
		},
		{
			"imgUrl": "https://guesseu.scene7.com/is/image/GuessEU/M63H24W7JF0-L302-ALTGHOST?wid=1500&fmt=jpeg&qlt=80&op_sharpen=0&op_usm=1.0,1.0,5,0&iccEmbed=0",
			"name": "CHECK PRINT SHIRT",
			"price": 100,
			"discountedPrice": 2000,
			"type": "shirts",
			"description": "100% cotton double printed dress."
		},
		{
			"imgUrl": "https://guesseu.scene7.com/is/image/GuessEU/FLGLO4FAL12-BEIBR?wid=700&amp;fmt=jpeg&amp;qlt=80&amp;op_sharpen=0&amp;op_usm=1.0,1.0,5,0&amp;iccEmbed=0",
			"name": "GLORIA Shoes",
			"price": 100,
			"discountedPrice": 2000,
			"type": "shoes",
			"description": "100% cotton double printed dress."
		},
		{
			"imgUrl": "https://i.ibb.co/D957b79/b1.png",
			"name": "CATE RIGID BAG",
			"price": 100,
			"discountedPrice": 2000,
			"type": "bags",
			"description": "100% cotton double printed dress."
		},
		{
			"imgUrl": "http://guesseu.scene7.com/is/image/GuessEU/WC0001FMSWC-G5?wid=520&fmt=jpeg&qlt=80&op_sharpen=0&op_usm=1.0,1.0,5,0&iccEmbed=0",
			"name": "GUESS CONNECT WATCH",
			"price": 100,
			"discountedPrice": 2000,
			"type": "watches",
			"description": "100% cotton double printed dress."
		},
		{
			"imgUrl": "https://guesseu.scene7.com/is/image/GuessEU/AW6308VIS03-SAP?wid=700&amp;fmt=jpeg&amp;qlt=80&amp;op_sharpen=0&amp;op_usm=1.0,1.0,5,0&amp;iccEmbed=0",
			"name": "'70s RETRO GLAM SCARF",
			"price": 100,
			"discountedPrice": 2000,
			"type": "scarfs",
			"description": "100% cotton double printed dress."
		},
		{
			"imgUrl": "https://i.ibb.co/SNVyv7N/shirt1.jpg",
			"name": "CHECK PRINT SHIRT",
			"price": 200,
			"discountedPrice": 2000,
			"type": "shirts",
			"description": "100% cotton double printed dress."
		},
		{
			"imgUrl": "https://i.ibb.co/WPpJmz0/ss1.webp",
			"name": "GLORIA Shoes",
			"price": 200,
			"discountedPrice": 2000,
			"type": "shoes",
			"description": "100% cotton double printed dress."
		},
		{
			"imgUrl": "https://i.ibb.co/wcVj87s/s2.png",
			"name": "CATE RIGID BAG",
			"price": 200,
			"discountedPrice": 2000,
			"type": "bags",
			"description": "100% cotton double printed dress."
		},
		{
			"imgUrl": "https://i.ibb.co/Zg3Bkhh/w1.jpg",
			"name": "GUESS CONNECT WATCH",
			"price": 200,
			"discountedPrice": 2000,
			"type": "watches",
			"description": "100% cotton double printed dress."
		},
		{
			"imgUrl": "https://i.ibb.co/CWNrHCb/sc1.jpg",
			"name": "'70s RETRO GLAM SCARF",
			"price": 200,
			"discountedPrice": 2000,
			"type": "scarfs",
			"description": "100% cotton double printed dress."
		},
		{
			"imgUrl": "https://i.ibb.co/JC61ngd/shirt.jpg",
			"name": "CHECK PRINT SHIRT",
			"price": 300,
			"discountedPrice": 2000,
			"type": "shirts",
			"description": "100% cotton double printed dress."
		},
		{
			"imgUrl": "https://i.ibb.co/zr0Yqch/ss2.png",
			"name": "GLORIA Shoes",
			"price": 300,
			"discountedPrice": 2000,
			"type": "shoes",
			"description": "100% cotton double printed dress."
		},
		{
			"imgUrl": "https://i.ibb.co/mBk0Pqh/s3.jpg",
			"name": "CATE RIGID BAG",
			"price": 300,
			"discountedPrice": 2000,
			"type": "bags",
			"description": "100% cotton double printed dress."
		},
		{
			"imgUrl": "https://i.ibb.co/BVSLV2h/w2.jpg",
			"name": "GUESS CONNECT WATCH",
			"price": 300,
			"discountedPrice": 2000,
			"type": "watches",
			"description": "100% cotton double printed dress."
		},
		{
			"imgUrl": "https://i.ibb.co/MD3Z1tQ/sc2.webp",
			"name": "'70s RETRO GLAM SCARF",
			"price": 300,
			"discountedPrice": 2000,
			"type": "scarfs",
			"description": "100% cotton double printed dress."
		},
		{
			"imgUrl": "https://i.ibb.co/tbgvdxb/Shirt-PNG-Download-Image.png",
			"name": "CHECK PRINT SHIRT",
			"price": 400,
			"discountedPrice": 2000,
			"type": "shirts",
			"description": "100% cotton double printed dress."
		},
		{
			"imgUrl": "https://i.ibb.co/85jkr3h/ss3.jpg",
			"name": "GLORIA Shoes",
			"price": 400,
			"discountedPrice": 2000,
			"type": "shoes",
			"description": "100% cotton double printed dress."
		},
		{
			"imgUrl": "https://guesseu.scene7.com/is/image/GuessEU/HWVG6216060-TAN?wid=700&amp;fmt=jpeg&amp;qlt=80&amp;op_sharpen=0&amp;op_usm=1.0,1.0,5,0&amp;iccEmbed=0",
			"name": "CATE RIGID BAG",
			"price": 400,
			"discountedPrice": 2000,
			"type": "bags",
			"description": "100% cotton double printed dress."
		},
		{
			"imgUrl": "https://i.ibb.co/xGJYgj3/w3.jpg",
			"name": "GUESS CONNECT WATCH",
			"price": 400,
			"discountedPrice": 2000,
			"type": "watches",
			"description": "100% cotton double printed dress."
		},
		{
			"imgUrl": "https://i.ibb.co/8jqMg8y/sc3.jpg",
			"name": "'70s RETRO GLAM SCARF",
			"price": 400,
			"discountedPrice": 2000,
			"type": "scarfs",
			"description": "100% cotton double printed dress."
		},
		{
			"imgUrl": "https://guesseu.scene7.com/is/image/GuessEU/M63H24W7JF0-L302-ALTGHOST?wid=1500&fmt=jpeg&qlt=80&op_sharpen=0&op_usm=1.0,1.0,5,0&iccEmbed=0",
			"name": "CHECK PRINT SHIRT",
			"price": 100,
			"discountedPrice": 2000,
			"type": "shirts",
			"description": "100% cotton double printed dress."
		},
		{
			"imgUrl": "https://guesseu.scene7.com/is/image/GuessEU/FLGLO4FAL12-BEIBR?wid=700&amp;fmt=jpeg&amp;qlt=80&amp;op_sharpen=0&amp;op_usm=1.0,1.0,5,0&amp;iccEmbed=0",
			"name": "GLORIA Shoes",
			"price": 100,
			"discountedPrice": 2000,
			"type": "shoes",
			"description": "100% cotton double printed dress."
		},
		{
			"imgUrl": "https://i.ibb.co/D957b79/b1.png",
			"name": "CATE RIGID BAG",
			"price": 100,
			"discountedPrice": 2000,
			"type": "bags",
			"description": "100% cotton double printed dress."
		},
		{
			"imgUrl": "http://guesseu.scene7.com/is/image/GuessEU/WC0001FMSWC-G5?wid=520&fmt=jpeg&qlt=80&op_sharpen=0&op_usm=1.0,1.0,5,0&iccEmbed=0",
			"name": "GUESS CONNECT WATCH",
			"price": 100,
			"discountedPrice": 2000,
			"type": "watches",
			"description": "100% cotton double printed dress."
		},
		{
			"imgUrl": "https://guesseu.scene7.com/is/image/GuessEU/AW6308VIS03-SAP?wid=700&amp;fmt=jpeg&amp;qlt=80&amp;op_sharpen=0&amp;op_usm=1.0,1.0,5,0&amp;iccEmbed=0",
			"name": "'70s RETRO GLAM SCARF",
			"price": 100,
			"discountedPrice": 2000,
			"type": "scarfs",
			"description": "100% cotton double printed dress."
		},
		{
			"imgUrl": "https://i.ibb.co/SNVyv7N/shirt1.jpg",
			"name": "CHECK PRINT SHIRT",
			"price": 200,
			"discountedPrice": 2000,
			"type": "shirts",
			"description": "100% cotton double printed dress."
		},
		{
			"imgUrl": "https://i.ibb.co/WPpJmz0/ss1.webp",
			"name": "GLORIA Shoes",
			"price": 200,
			"discountedPrice": 2000,
			"type": "shoes",
			"description": "100% cotton double printed dress."
		},
		{
			"imgUrl": "https://i.ibb.co/wcVj87s/s2.png",
			"name": "CATE RIGID BAG",
			"price": 200,
			"discountedPrice": 2000,
			"type": "bags",
			"description": "100% cotton double printed dress."
		},
		{
			"imgUrl": "https://i.ibb.co/Zg3Bkhh/w1.jpg",
			"name": "GUESS CONNECT WATCH",
			"price": 200,
			"discountedPrice": 2000,
			"type": "watches",
			"description": "100% cotton double printed dress."
		},
		{
			"imgUrl": "https://i.ibb.co/CWNrHCb/sc1.jpg",
			"name": "'70s RETRO GLAM SCARF",
			"price": 200,
			"discountedPrice": 2000,
			"type": "scarfs",
			"description": "100% cotton double printed dress."
		},
		{
			"imgUrl": "https://i.ibb.co/JC61ngd/shirt.jpg",
			"name": "CHECK PRINT SHIRT",
			"price": 300,
			"discountedPrice": 2000,
			"type": "shirts",
			"description": "100% cotton double printed dress."
		},
		{
			"imgUrl": "https://i.ibb.co/zr0Yqch/ss2.png",
			"name": "GLORIA Shoes",
			"price": 300,
			"discountedPrice": 2000,
			"type": "shoes",
			"description": "100% cotton double printed dress."
		},
		{
			"imgUrl": "https://i.ibb.co/mBk0Pqh/s3.jpg",
			"name": "CATE RIGID BAG",
			"price": 300,
			"discountedPrice": 2000,
			"type": "bags",
			"description": "100% cotton double printed dress."
		},
		{
			"imgUrl": "https://i.ibb.co/BVSLV2h/w2.jpg",
			"name": "GUESS CONNECT WATCH",
			"price": 300,
			"discountedPrice": 2000,
			"type": "watches",
			"description": "100% cotton double printed dress."
		},
		{
			"imgUrl": "https://i.ibb.co/MD3Z1tQ/sc2.webp",
			"name": "'70s RETRO GLAM SCARF",
			"price": 300,
			"discountedPrice": 2000,
			"type": "scarfs",
			"description": "100% cotton double printed dress."
		},
		{
			"imgUrl": "https://i.ibb.co/tbgvdxb/Shirt-PNG-Download-Image.png",
			"name": "CHECK PRINT SHIRT",
			"price": 400,
			"discountedPrice": 2000,
			"type": "shirts",
			"description": "100% cotton double printed dress."
		},
		{
			"imgUrl": "https://i.ibb.co/85jkr3h/ss3.jpg",
			"name": "GLORIA Shoes",
			"price": 400,
			"discountedPrice": 2000,
			"type": "shoes",
			"description": "100% cotton double printed dress."
		},
		{
			"imgUrl": "https://guesseu.scene7.com/is/image/GuessEU/HWVG6216060-TAN?wid=700&amp;fmt=jpeg&amp;qlt=80&amp;op_sharpen=0&amp;op_usm=1.0,1.0,5,0&amp;iccEmbed=0",
			"name": "CATE RIGID BAG",
			"price": 400,
			"discountedPrice": 2000,
			"type": "bags",
			"description": "100% cotton double printed dress."
		},
		{
			"imgUrl": "https://i.ibb.co/xGJYgj3/w3.jpg",
			"name": "GUESS CONNECT WATCH",
			"price": 400,
			"discountedPrice": 2000,
			"type": "watches",
			"description": "100% cotton double printed dress."
		},
		{
			"imgUrl": "https://i.ibb.co/8jqMg8y/sc3.jpg",
			"name": "'70s RETRO GLAM SCARF",
			"price": 400,
			"discountedPrice": 2000,
			"type": "scarfs",
			"description": "100% cotton double printed dress."
		}
	]
}